Permitronix/__init__.py
Permitronix/permission_level.py
Permitronix/permission_node.py
Permitronix/permission_table.py
permitronix/__init__.py
permitronix/db.py
permitronix/jelly.py
permitronix/permission_level.py
permitronix/permission_node.py
permitronix/permission_table.py
Permitronix-1.1.3.dist-info/METADATA
Permitronix-1.1.3.dist-info/WHEEL
Permitronix-1.1.3.dist-info/top_level.txt
Permitronix-1.1.3.dist-info/RECORD
