Metadata-Version: 2.1
Name: Permitronix
Version: 1.1.3
Summary: A py permission management module.
Home-page: https://github.com/hsn8086/Permitronix
Author: hsn
Author-email: hsn1919810@gmail.com
License: MIT
